maltego_stix2/__init__.py
maltego_stix2/config.py
maltego_stix2/entities.py
maltego_stix2/util.py
maltego_stix2-2.1.7.dist-info/AUTHORS
maltego_stix2-2.1.7.dist-info/LICENSE
maltego_stix2-2.1.7.dist-info/METADATA
maltego_stix2-2.1.7.dist-info/WHEEL
maltego_stix2-2.1.7.dist-info/top_level.txt
maltego_stix2-2.1.7.dist-info/RECORD
