Metadata-Version: 2.1
Name: maltego-stix2
Version: 2.1.7
Summary: Helper utilities for building Maltego transforms that consume or produce data in STIX2 format.
Home-page: https://github.com/maltegotransforms/maltego-stix2
Author: ANSSI, Samuel Hassine, Maltego Technologies GmbH
Author-email: moa.amr.cossi@ssi.gouv.fr, samuel.hassine@luatix.org, support@maltego.com
License: Apache License 2.0
License-File: LICENSE
License-File: AUTHORS
Requires-Dist: Pillow (>=9.5.0)
Requires-Dist: maltego-trx (~=1.6.1)
Requires-Dist: stix2 (~=3.0.1)
Requires-Dist: python-dateutil (>=2.8.1)
